{
  "Comments": "Workflow Composition 10 - 3 groups",
  "NumTasks": 5,
  "RequestNumEvents": 1155000,
  "Taskset1": {
    "KeepOutput": false,
    "Memory": 2000,
    "Multicore": 1,
    "RequiresGPU": "forbidden",
    "ScramArch": [
      "el8_amd64_gcc10"
    ],
    "SizePerEvent": 807.0317070422535,
    "TimePerEvent": 1.6348524382189265,
    "GroupName": "group_5",
    "GroupInputEvents": 1365
  },
  "Taskset2": {
    "KeepOutput": false,
    "Memory": 4000,
    "Multicore": 2,
    "RequiresGPU": "forbidden",
    "ScramArch": [
      "el8_amd64_gcc10"
    ],
    "SizePerEvent": 1200,
    "TimePerEvent": 30,
    "InputTaskset": "Taskset1",
    "GroupName": "group_5",
    "GroupInputEvents": 1365
  },
  "Taskset3": {
    "KeepOutput": true,
    "Memory": 8000,
    "Multicore": 4,
    "RequiresGPU": "forbidden",
    "ScramArch": [
      "el8_amd64_gcc10"
    ],
    "SizePerEvent": 550,
    "TimePerEvent": 6,
    "InputTaskset": "Taskset2",
    "GroupName": "group_7",
    "GroupInputEvents": 6171
  },
  "Taskset4": {
    "KeepOutput": true,
    "Memory": 16000,
    "Multicore": 8,
    "RequiresGPU": "forbidden",
    "ScramArch": [
      "el8_amd64_gcc11"
    ],
    "SizePerEvent": 150,
    "TimePerEvent": 1,
    "InputTaskset": "Taskset3",
    "GroupName": "group_7",
    "GroupInputEvents": 6171
  },
  "Taskset5": {
    "KeepOutput": true,
    "Memory": 24000,
    "Multicore": 12,
    "RequiresGPU": "forbidden",
    "ScramArch": [
      "el8_amd64_gcc11"
    ],
    "SizePerEvent": 30.782,
    "TimePerEvent": 0.3402,
    "InputTaskset": "Taskset4",
    "GroupName": "group_4",
    "GroupInputEvents": 126984
  },
  "CompositionNumber": 10
}