[
  {
    "group_id": "group_0",
    "task_ids": [
      "Taskset1"
    ],
    "entry_point_task": "Taskset1",
    "exit_point_task": "Taskset1",
    "input_task": null,
    "resource_metrics": {
      "cpu": {
        "max_cores": 8,
        "cpu_seconds": 345587.2,
        "utilization_ratio": 1.0
      },
      "memory": {
        "max_mb": 8000,
        "min_mb": 8000,
        "occupancy": 1.0
      },
      "throughput": {
        "total_eps": 0.03289473684210526,
        "max_eps": 0.03289473684210526,
        "min_eps": 0.03289473684210526
      },
      "io": {
        "read_remote_mb": 0.0,
        "write_local_mb": 8881.25,
        "write_remote_mb": 8881.25,
        "read_remote_per_event_mb": 0.0,
        "write_local_per_event_mb": 0.78125,
        "write_remote_per_event_mb": 0.78125
      },
      "accelerator": {
        "types": []
      }
    },
    "utilization_metrics": {
      "resource_utilization": 1.0,
      "event_throughput": 0.03289473684210526
    },
    "dependency_paths": [],
    "events_per_job": 11368
  },
  {
    "group_id": "group_1",
    "task_ids": [
      "Taskset2"
    ],
    "entry_point_task": "Taskset2",
    "exit_point_task": "Taskset2",
    "input_task": "Taskset1",
    "resource_metrics": {
      "cpu": {
        "max_cores": 8,
        "cpu_seconds": 345593.60000000003,
        "utilization_ratio": 1.0
      },
      "memory": {
        "max_mb": 8000,
        "min_mb": 8000,
        "occupancy": 1.0
      },
      "throughput": {
        "total_eps": 0.11363636363636362,
        "max_eps": 0.11363636363636362,
        "min_eps": 0.11363636363636362
      },
      "io": {
        "read_remote_mb": 30681.25,
        "write_local_mb": 82072.34375,
        "write_remote_mb": 82072.34375,
        "read_remote_per_event_mb": 0.78125,
        "write_local_per_event_mb": 2.08984375,
        "write_remote_per_event_mb": 2.08984375
      },
      "accelerator": {
        "types": []
      }
    },
    "utilization_metrics": {
      "resource_utilization": 1.0,
      "event_throughput": 0.11363636363636362
    },
    "dependency_paths": [],
    "events_per_job": 39272
  },
  {
    "group_id": "group_10",
    "task_ids": [
      "Taskset2",
      "Taskset3",
      "Taskset4"
    ],
    "entry_point_task": "Taskset2",
    "exit_point_task": "Taskset4",
    "input_task": "Taskset1",
    "resource_metrics": {
      "cpu": {
        "max_cores": 8,
        "cpu_seconds": 345577.2,
        "utilization_ratio": 1.0
      },
      "memory": {
        "max_mb": 8000,
        "min_mb": 8000,
        "occupancy": 1.0
      },
      "throughput": {
        "total_eps": 0.040983606557377046,
        "max_eps": 0.3571428571428572,
        "min_eps": 0.07812499999999999
      },
      "io": {
        "read_remote_mb": 11064.84375,
        "write_local_mb": 35822.431640625,
        "write_remote_mb": 6223.974609375,
        "read_remote_per_event_mb": 0.78125,
        "write_local_per_event_mb": 2.529296875,
        "write_remote_per_event_mb": 0.439453125
      },
      "accelerator": {
        "types": []
      }
    },
    "utilization_metrics": {
      "resource_utilization": 1.0,
      "event_throughput": 0.040983606557377046
    },
    "dependency_paths": [
      [
        "Taskset2",
        "Taskset3"
      ],
      [
        "Taskset2",
        "Taskset3",
        "Taskset4"
      ],
      [
        "Taskset3",
        "Taskset4"
      ]
    ],
    "events_per_job": 14163
  },
  {
    "group_id": "group_11",
    "task_ids": [
      "Taskset3",
      "Taskset4",
      "Taskset5"
    ],
    "entry_point_task": "Taskset3",
    "exit_point_task": "Taskset5",
    "input_task": "Taskset2",
    "resource_metrics": {
      "cpu": {
        "max_cores": 8,
        "cpu_seconds": 345600.0,
        "utilization_ratio": 1.0
      },
      "memory": {
        "max_mb": 8000,
        "min_mb": 8000,
        "occupancy": 1.0
      },
      "throughput": {
        "total_eps": 0.0625,
        "max_eps": 2.5,
        "min_eps": 0.078125
      },
      "io": {
        "read_remote_mb": 45140.625,
        "write_local_mb": 9703.125,
        "write_remote_mb": 9703.125,
        "read_remote_per_event_mb": 2.08984375,
        "write_local_per_event_mb": 0.44921875,
        "write_remote_per_event_mb": 0.44921875
      },
      "accelerator": {
        "types": []
      }
    },
    "utilization_metrics": {
      "resource_utilization": 1.0,
      "event_throughput": 0.0625
    },
    "dependency_paths": [
      [
        "Taskset3",
        "Taskset4"
      ],
      [
        "Taskset3",
        "Taskset4",
        "Taskset5"
      ],
      [
        "Taskset4",
        "Taskset5"
      ]
    ],
    "events_per_job": 21600
  },
  {
    "group_id": "group_12",
    "task_ids": [
      "Taskset1",
      "Taskset2",
      "Taskset3",
      "Taskset4"
    ],
    "entry_point_task": "Taskset1",
    "exit_point_task": "Taskset4",
    "input_task": null,
    "resource_metrics": {
      "cpu": {
        "max_cores": 8,
        "cpu_seconds": 345568.8,
        "utilization_ratio": 1.0
      },
      "memory": {
        "max_mb": 8000,
        "min_mb": 8000,
        "occupancy": 1.0
      },
      "throughput": {
        "total_eps": 0.018248175182481754,
        "max_eps": 0.35714285714285715,
        "min_eps": 0.03289473684210526
      },
      "io": {
        "read_remote_mb": 0.0,
        "write_local_mb": 20876.30859375,
        "write_remote_mb": 2771.19140625,
        "read_remote_per_event_mb": 0.0,
        "write_local_per_event_mb": 3.310546875,
        "write_remote_per_event_mb": 0.439453125
      },
      "accelerator": {
        "types": []
      }
    },
    "utilization_metrics": {
      "resource_utilization": 1.0,
      "event_throughput": 0.018248175182481754
    },
    "dependency_paths": [
      [
        "Taskset1",
        "Taskset2"
      ],
      [
        "Taskset1",
        "Taskset2",
        "Taskset3"
      ],
      [
        "Taskset1",
        "Taskset2",
        "Taskset3",
        "Taskset4"
      ],
      [
        "Taskset2",
        "Taskset3"
      ],
      [
        "Taskset2",
        "Taskset3",
        "Taskset4"
      ],
      [
        "Taskset3",
        "Taskset4"
      ]
    ],
    "events_per_job": 6306
  },
  {
    "group_id": "group_13",
    "task_ids": [
      "Taskset2",
      "Taskset3",
      "Taskset4",
      "Taskset5"
    ],
    "entry_point_task": "Taskset2",
    "exit_point_task": "Taskset5",
    "input_task": "Taskset1",
    "resource_metrics": {
      "cpu": {
        "max_cores": 8,
        "cpu_seconds": 345588.0,
        "utilization_ratio": 1.0
      },
      "memory": {
        "max_mb": 8000,
        "min_mb": 8000,
        "occupancy": 1.0
      },
      "throughput": {
        "total_eps": 0.04032258064516129,
        "max_eps": 2.5,
        "min_eps": 0.078125
      },
      "io": {
        "read_remote_mb": 10886.71875,
        "write_local_mb": 35381.8359375,
        "write_remote_mb": 6259.86328125,
        "read_remote_per_event_mb": 0.78125,
        "write_local_per_event_mb": 2.5390625,
        "write_remote_per_event_mb": 0.44921875
      },
      "accelerator": {
        "types": []
      }
    },
    "utilization_metrics": {
      "resource_utilization": 1.0,
      "event_throughput": 0.04032258064516129
    },
    "dependency_paths": [
      [
        "Taskset2",
        "Taskset3"
      ],
      [
        "Taskset2",
        "Taskset3",
        "Taskset4"
      ],
      [
        "Taskset2",
        "Taskset3",
        "Taskset4",
        "Taskset5"
      ],
      [
        "Taskset3",
        "Taskset4"
      ],
      [
        "Taskset3",
        "Taskset4",
        "Taskset5"
      ],
      [
        "Taskset4",
        "Taskset5"
      ]
    ],
    "events_per_job": 13935
  },
  {
    "group_id": "group_14",
    "task_ids": [
      "Taskset1",
      "Taskset2",
      "Taskset3",
      "Taskset4",
      "Taskset5"
    ],
    "entry_point_task": "Taskset1",
    "exit_point_task": "Taskset5",
    "input_task": null,
    "resource_metrics": {
      "cpu": {
        "max_cores": 8,
        "cpu_seconds": 345552.0,
        "utilization_ratio": 1.0
      },
      "memory": {
        "max_mb": 8000,
        "min_mb": 8000,
        "occupancy": 1.0
      },
      "throughput": {
        "total_eps": 0.018115942028985508,
        "max_eps": 2.5,
        "min_eps": 0.03289473684210526
      },
      "io": {
        "read_remote_mb": 0.0,
        "write_local_mb": 20785.15625,
        "write_remote_mb": 2812.109375,
        "read_remote_per_event_mb": 0.0,
        "write_local_per_event_mb": 3.3203125,
        "write_remote_per_event_mb": 0.44921875
      },
      "accelerator": {
        "types": []
      }
    },
    "utilization_metrics": {
      "resource_utilization": 1.0,
      "event_throughput": 0.018115942028985508
    },
    "dependency_paths": [
      [
        "Taskset1",
        "Taskset2"
      ],
      [
        "Taskset1",
        "Taskset2",
        "Taskset3"
      ],
      [
        "Taskset1",
        "Taskset2",
        "Taskset3",
        "Taskset4"
      ],
      [
        "Taskset1",
        "Taskset2",
        "Taskset3",
        "Taskset4",
        "Taskset5"
      ],
      [
        "Taskset2",
        "Taskset3"
      ],
      [
        "Taskset2",
        "Taskset3",
        "Taskset4"
      ],
      [
        "Taskset2",
        "Taskset3",
        "Taskset4",
        "Taskset5"
      ],
      [
        "Taskset3",
        "Taskset4"
      ],
      [
        "Taskset3",
        "Taskset4",
        "Taskset5"
      ],
      [
        "Taskset4",
        "Taskset5"
      ]
    ],
    "events_per_job": 6260
  },
  {
    "group_id": "group_2",
    "task_ids": [
      "Taskset3"
    ],
    "entry_point_task": "Taskset3",
    "exit_point_task": "Taskset3",
    "input_task": "Taskset2",
    "resource_metrics": {
      "cpu": {
        "max_cores": 8,
        "cpu_seconds": 345600.0,
        "utilization_ratio": 1.0
      },
      "memory": {
        "max_mb": 8000,
        "min_mb": 8000,
        "occupancy": 1.0
      },
      "throughput": {
        "total_eps": 0.078125,
        "max_eps": 0.078125,
        "min_eps": 0.078125
      },
      "io": {
        "read_remote_mb": 56425.78125,
        "write_local_mb": 10151.3671875,
        "write_remote_mb": 10151.3671875,
        "read_remote_per_event_mb": 2.08984375,
        "write_local_per_event_mb": 0.3759765625,
        "write_remote_per_event_mb": 0.3759765625
      },
      "accelerator": {
        "types": []
      }
    },
    "utilization_metrics": {
      "resource_utilization": 1.0,
      "event_throughput": 0.078125
    },
    "dependency_paths": [],
    "events_per_job": 27000
  },
  {
    "group_id": "group_3",
    "task_ids": [
      "Taskset4"
    ],
    "entry_point_task": "Taskset4",
    "exit_point_task": "Taskset4",
    "input_task": "Taskset3",
    "resource_metrics": {
      "cpu": {
        "max_cores": 8,
        "cpu_seconds": 345598.39999999997,
        "utilization_ratio": 1.0
      },
      "memory": {
        "max_mb": 8000,
        "min_mb": 8000,
        "occupancy": 0.9999999999999999
      },
      "throughput": {
        "total_eps": 0.3571428571428572,
        "max_eps": 0.3571428571428572,
        "min_eps": 0.3571428571428572
      },
      "io": {
        "read_remote_mb": 46406.03515625,
        "write_local_mb": 7834.78515625,
        "write_remote_mb": 7834.78515625,
        "read_remote_per_event_mb": 0.3759765625,
        "write_local_per_event_mb": 0.0634765625,
        "write_remote_per_event_mb": 0.0634765625
      },
      "accelerator": {
        "types": []
      }
    },
    "utilization_metrics": {
      "resource_utilization": 1.0,
      "event_throughput": 0.3571428571428572
    },
    "dependency_paths": [],
    "events_per_job": 123428
  },
  {
    "group_id": "group_4",
    "task_ids": [
      "Taskset5"
    ],
    "entry_point_task": "Taskset5",
    "exit_point_task": "Taskset5",
    "input_task": "Taskset4",
    "resource_metrics": {
      "cpu": {
        "max_cores": 8,
        "cpu_seconds": 345600.0,
        "utilization_ratio": 1.0
      },
      "memory": {
        "max_mb": 8000,
        "min_mb": 8000,
        "occupancy": 1.0
      },
      "throughput": {
        "total_eps": 2.5,
        "max_eps": 2.5,
        "min_eps": 2.5
      },
      "io": {
        "read_remote_mb": 54843.75,
        "write_local_mb": 8437.5,
        "write_remote_mb": 8437.5,
        "read_remote_per_event_mb": 0.0634765625,
        "write_local_per_event_mb": 0.009765625,
        "write_remote_per_event_mb": 0.009765625
      },
      "accelerator": {
        "types": []
      }
    },
    "utilization_metrics": {
      "resource_utilization": 1.0,
      "event_throughput": 2.5
    },
    "dependency_paths": [],
    "events_per_job": 864000
  },
  {
    "group_id": "group_5",
    "task_ids": [
      "Taskset1",
      "Taskset2"
    ],
    "entry_point_task": "Taskset1",
    "exit_point_task": "Taskset2",
    "input_task": null,
    "resource_metrics": {
      "cpu": {
        "max_cores": 8,
        "cpu_seconds": 345587.2,
        "utilization_ratio": 1.0
      },
      "memory": {
        "max_mb": 8000,
        "min_mb": 8000,
        "occupancy": 1.0
      },
      "throughput": {
        "total_eps": 0.025510204081632654,
        "max_eps": 0.11363636363636363,
        "min_eps": 0.03289473684210527
      },
      "io": {
        "read_remote_mb": 0.0,
        "write_local_mb": 25311.5625,
        "write_remote_mb": 18424.0625,
        "read_remote_per_event_mb": 0.0,
        "write_local_per_event_mb": 2.87109375,
        "write_remote_per_event_mb": 2.08984375
      },
      "accelerator": {
        "types": []
      }
    },
    "utilization_metrics": {
      "resource_utilization": 1.0,
      "event_throughput": 0.025510204081632654
    },
    "dependency_paths": [
      [
        "Taskset1",
        "Taskset2"
      ]
    ],
    "events_per_job": 8816
  },
  {
    "group_id": "group_6",
    "task_ids": [
      "Taskset2",
      "Taskset3"
    ],
    "entry_point_task": "Taskset2",
    "exit_point_task": "Taskset3",
    "input_task": "Taskset1",
    "resource_metrics": {
      "cpu": {
        "max_cores": 8,
        "cpu_seconds": 345578.4,
        "utilization_ratio": 1.0
      },
      "memory": {
        "max_mb": 8000,
        "min_mb": 8000,
        "occupancy": 0.9999999999999999
      },
      "throughput": {
        "total_eps": 0.046296296296296294,
        "max_eps": 0.11363636363636363,
        "min_eps": 0.078125
      },
      "io": {
        "read_remote_mb": 12499.21875,
        "write_local_mb": 39450.6591796875,
        "write_remote_mb": 6015.2490234375,
        "read_remote_per_event_mb": 0.78125,
        "write_local_per_event_mb": 2.4658203125,
        "write_remote_per_event_mb": 0.3759765625
      },
      "accelerator": {
        "types": []
      }
    },
    "utilization_metrics": {
      "resource_utilization": 1.0,
      "event_throughput": 0.046296296296296294
    },
    "dependency_paths": [
      [
        "Taskset2",
        "Taskset3"
      ]
    ],
    "events_per_job": 15999
  },
  {
    "group_id": "group_7",
    "task_ids": [
      "Taskset3",
      "Taskset4"
    ],
    "entry_point_task": "Taskset3",
    "exit_point_task": "Taskset4",
    "input_task": "Taskset2",
    "resource_metrics": {
      "cpu": {
        "max_cores": 8,
        "cpu_seconds": 345586.80000000005,
        "utilization_ratio": 1.0
      },
      "memory": {
        "max_mb": 8000,
        "min_mb": 8000,
        "occupancy": 0.9999999999999999
      },
      "throughput": {
        "total_eps": 0.0641025641025641,
        "max_eps": 0.35714285714285715,
        "min_eps": 0.078125
      },
      "io": {
        "read_remote_mb": 46296.30859375,
        "write_local_mb": 9735.205078125,
        "write_remote_mb": 9735.205078125,
        "read_remote_per_event_mb": 2.08984375,
        "write_local_per_event_mb": 0.439453125,
        "write_remote_per_event_mb": 0.439453125
      },
      "accelerator": {
        "types": []
      }
    },
    "utilization_metrics": {
      "resource_utilization": 1.0,
      "event_throughput": 0.0641025641025641
    },
    "dependency_paths": [
      [
        "Taskset3",
        "Taskset4"
      ]
    ],
    "events_per_job": 22153
  },
  {
    "group_id": "group_8",
    "task_ids": [
      "Taskset4",
      "Taskset5"
    ],
    "entry_point_task": "Taskset4",
    "exit_point_task": "Taskset5",
    "input_task": "Taskset3",
    "resource_metrics": {
      "cpu": {
        "max_cores": 8,
        "cpu_seconds": 345600.0,
        "utilization_ratio": 1.0
      },
      "memory": {
        "max_mb": 8000,
        "min_mb": 8000,
        "occupancy": 1.0
      },
      "throughput": {
        "total_eps": 0.3125,
        "max_eps": 2.5,
        "min_eps": 0.35714285714285715
      },
      "io": {
        "read_remote_mb": 40605.46875,
        "write_local_mb": 7910.15625,
        "write_remote_mb": 7910.15625,
        "read_remote_per_event_mb": 0.3759765625,
        "write_local_per_event_mb": 0.0732421875,
        "write_remote_per_event_mb": 0.0732421875
      },
      "accelerator": {
        "types": []
      }
    },
    "utilization_metrics": {
      "resource_utilization": 1.0,
      "event_throughput": 0.3125
    },
    "dependency_paths": [
      [
        "Taskset4",
        "Taskset5"
      ]
    ],
    "events_per_job": 108000
  },
  {
    "group_id": "group_9",
    "task_ids": [
      "Taskset1",
      "Taskset2",
      "Taskset3"
    ],
    "entry_point_task": "Taskset1",
    "exit_point_task": "Taskset3",
    "input_task": null,
    "resource_metrics": {
      "cpu": {
        "max_cores": 8,
        "cpu_seconds": 345592.0,
        "utilization_ratio": 1.0
      },
      "memory": {
        "max_mb": 8000,
        "min_mb": 8000,
        "occupancy": 1.0
      },
      "throughput": {
        "total_eps": 0.019230769230769232,
        "max_eps": 0.11363636363636363,
        "min_eps": 0.03289473684210526
      },
      "io": {
        "read_remote_mb": 0.0,
        "write_local_mb": 21580.029296875,
        "write_remote_mb": 2498.740234375,
        "read_remote_per_event_mb": 0.0,
        "write_local_per_event_mb": 3.2470703125,
        "write_remote_per_event_mb": 0.3759765625
      },
      "accelerator": {
        "types": []
      }
    },
    "utilization_metrics": {
      "resource_utilization": 1.0,
      "event_throughput": 0.019230769230769232
    },
    "dependency_paths": [
      [
        "Taskset1",
        "Taskset2"
      ],
      [
        "Taskset1",
        "Taskset2",
        "Taskset3"
      ],
      [
        "Taskset2",
        "Taskset3"
      ]
    ],
    "events_per_job": 6646
  }
]